highlighter/__init__.py
highlighter/dockr.py
highlighter/highlight.py
pyhighlighter_c-1.0.0.dist-info/METADATA
pyhighlighter_c-1.0.0.dist-info/WHEEL
pyhighlighter_c-1.0.0.dist-info/entry_points.txt
pyhighlighter_c-1.0.0.dist-info/top_level.txt
pyhighlighter_c-1.0.0.dist-info/RECORD
