Metadata-Version: 2.4
Name: pyhighlighter-c
Version: 1.0.0
Summary: Advanced syntax highlighter with built-in compiler
Home-page: https://github.com/yourusername/pyhighlighter
Author: Jay C
Author-email: your.email@example.com
Keywords: syntax highlighting code editor compiler
Classifier: Development Status :: 4 - Beta
Classifier: Intended Audience :: Developers
Classifier: License :: OSI Approved :: MIT License
Classifier: Programming Language :: Python :: 3
Classifier: Operating System :: OS Independent
Requires-Python: >=3.7
Requires-Dist: pygments>=2.10.0
Dynamic: author
Dynamic: author-email
Dynamic: classifier
Dynamic: description
Dynamic: description-content-type
Dynamic: home-page
Dynamic: keywords
Dynamic: requires-dist
Dynamic: requires-python
Dynamic: summary
